Metadata-Version: 1.0
Name: ursacl
Version: 0.1.0
Summary: python wrapper for ursa universal crypto library
Home-page: https://github.com/cam-parra/python-ursa
Author: Cam Parra, Vyacheslav Gudkov
Author-email: camilo.parra@evernym.com, vyacheslav.gudkov@dsr-company.com
License: Apache-2.0
Platform: UNKNOWN
